deep_linear_network/__init__.py
deep_linear_network/deep_linear_network.py
deep_linear_network-0.0.1.dist-info/LICENSE
deep_linear_network-0.0.1.dist-info/METADATA
deep_linear_network-0.0.1.dist-info/WHEEL
deep_linear_network-0.0.1.dist-info/top_level.txt
deep_linear_network-0.0.1.dist-info/RECORD
