Metadata-Version: 2.1
Name: deep-linear-network
Version: 0.0.1
Summary: Deep Linear Network - Pytorch
Home-page: https://github.com/lucidrains/deep-linear-network
Author: Phil Wang
Author-email: lucidrains@gmail.com
License: MIT
Keywords: artificial intelligence,attention mechanism
Platform: UNKNOWN
Classifier: Development Status :: 4 - Beta
Classifier: Intended Audience :: Developers
Classifier: Topic :: Scientific/Engineering :: Artificial Intelligence
Classifier: License :: OSI Approved :: MIT License
Classifier: Programming Language :: Python :: 3.6
Requires-Dist: torch
